{
    "name": "96a8e19f-31ed-4dd5-a150-cec811d06a2c",
    "type": "Microsoft.Authorization/roleDefinitions",
    "apiVersion": "2018-01-01-preview",
    "properties": {
        "roleName": "contoso-human-billing-admin",
        "description": "This role grants admin permissions over all billing resources.",
        "type": "customRole",
        "permissions": [
            {
                "actions": [
                    "Microsoft.Consumption/*",
                    "Microsoft.CostManagement/*",
                    "Microsoft.Billing/billingPeriods/read",
                    "Microsoft.Resources/subscriptions/read",
                    "Microsoft.Resources/subscriptions/resourceGroups/read",
                    "Microsoft.Support/*",
                    "Microsoft.Advisor/configurations/read",
                    "Microsoft.Advisor/recommendations/read",
                    "Microsoft.Management/managementGroups/read",
                    "Microsoft.Billing/billingProperty/read",
                    "Microsoft.Authorization/*/read",
                    "Microsoft.Blueprint/blueprintAssignments/*",
                    "Microsoft.Resources/subscriptions/resourceGroups/read",
                    "Microsoft.Resources/deployments/*"
                ],
                "notActions": [],
                "dataActions": [],
                "notDataActions": []
            }
        ],
        "assignableScopes": [
            "/"
        ]
    }
}